read_rkf/__init__.py
read_rkf/creat_archive.py
read_rkf/parserkf.py
read_rkf-0.1.1.dist-info/METADATA
read_rkf-0.1.1.dist-info/WHEEL
read_rkf-0.1.1.dist-info/RECORD
