Metadata-Version: 2.1
Name: read-rkf
Version: 0.1.1
Summary: 
Author: Dinga Wonanke
Requires-Python: >=3.9,<4.0
Classifier: Programming Language :: Python :: 3
Classifier: Programming Language :: Python :: 3.9
Classifier: Programming Language :: Python :: 3.10
Classifier: Programming Language :: Python :: 3.11
